sgtlibc/__init__.py
sgtlibc/__version__.py
sgtlibc/main.py
sgtlibc/LibcSearcher/__init__.py
sgtlibc/LibcSearcher/commons/__init__.py
sgtlibc/ROPgadgets/__init__.py
sgtlibc/libc-database/README.md
sgtlibc/libc-database/add
sgtlibc/libc-database/dump
sgtlibc/libc-database/find
sgtlibc/libc-database/get
sgtlibc/libc-database/identify
sgtlibc/libc-database/common/libc.sh
"sgtlibc/libc-database/db/default empty here , you should run sgtlibcsearcher --update for download database.txt"
sgtlibc/libc-database/db/dietlibc_0.26-3_i386.info
sgtlibc/libc-database/db/dietlibc_0.26-3_i386.symbols
sgtlibc/libc-database/db/dietlibc_0.27-7ubuntu1_i386.info
sgtlibc/libc-database/db/dietlibc_0.27-7ubuntu1_i386.symbols
sgtlibc/libc-database/db/dietlibc_0.29-2ubuntu1_i386.info
sgtlibc/libc-database/db/dietlibc_0.29-2ubuntu1_i386.symbols
sgtlibc/libc-database/db/dietlibc_0.29-8ubuntu1_i386.info
sgtlibc/libc-database/db/dietlibc_0.29-8ubuntu1_i386.symbols
sgtlibc/libc-database/db/dietlibc_0.30-1ubuntu2_i386.info
sgtlibc/libc-database/db/dietlibc_0.30-1ubuntu2_i386.symbols
sgtlibc/libc-database/db/dietlibc_0.30-4ubuntu1_i386.info
sgtlibc/libc-database/db/dietlibc_0.30-4ubuntu1_i386.symbols
sgtlibc/libc-database/db/dietlibc_0.30-7ubuntu1_i386.info
sgtlibc/libc-database/db/dietlibc_0.30-7ubuntu1_i386.symbols
sgtlibc/libc-database/db/dietlibc_0.31-1.2ubuntu1_i386.info
sgtlibc/libc-database/db/dietlibc_0.31-1.2ubuntu1_i386.symbols
sgtlibc/libc-database/db/dietlibc_0.31-1.2ubuntu2_i386.info
sgtlibc/libc-database/db/dietlibc_0.31-1.2ubuntu2_i386.symbols
sgtlibc/libc-database/db/dietlibc_0.31-1ubuntu3_i386.info
sgtlibc/libc-database/db/dietlibc_0.31-1ubuntu3_i386.symbols
sgtlibc/libc-database/db/glibc-2.12-1.212.el6.i686_2.symbols
sgtlibc/libc-database/db/glibc-2.12-4.el7.centos.x86_64.info
sgtlibc/libc-database/db/glibc-2.12-4.el7.centos.x86_64.symbols
sgtlibc/libc-database/db/glibc-2.17-317.el7.i686.info
sgtlibc/libc-database/db/glibc-2.17-317.el7.i686.symbols
sgtlibc-1.7.4.dist-info/LICENSE
sgtlibc-1.7.4.dist-info/METADATA
sgtlibc-1.7.4.dist-info/WHEEL
sgtlibc-1.7.4.dist-info/entry_points.txt
sgtlibc-1.7.4.dist-info/top_level.txt
sgtlibc-1.7.4.dist-info/RECORD
