Metadata-Version: 2.1
Name: sgtlibc
Version: 1.7.4
Summary: a offline python-lib for search libc function.for search version of libc.you can use like:`sgtlibc puts:aa0+read:140 --dump system binsh` or in python , like : `py:import sgtlibc;s = sgtlibc.LibcSearcher();s.add_condition('puts',0xaa0)`
Home-page: https://github.com/serfend/sgtlibc
Author: serfend
Author-email: serfend@foxmail.com
License: MIT Licence
Keywords: libcsearcher
Platform: any
Classifier: Development Status :: 5 - Production/Stable
Classifier: Environment :: Web Environment
Classifier: Intended Audience :: Developers
Classifier: License :: OSI Approved :: Apache Software License
Classifier: Natural Language :: English
Classifier: Operating System :: OS Independent
Classifier: Programming Language :: Python
Classifier: Programming Language :: Python :: 3
Classifier: Programming Language :: Python :: 3.7
Classifier: Programming Language :: Python :: 3.8
Classifier: Programming Language :: Python :: 3.9
Classifier: Programming Language :: Python :: 3.10
Classifier: Programming Language :: Python :: 3.11
Classifier: Programming Language :: Python :: 3 :: Only
Classifier: Programming Language :: Python :: Implementation :: CPython
Classifier: Programming Language :: Python :: Implementation :: PyPy
Classifier: Topic :: Software Development :: Libraries
Requires-Python: >=3.7, <4
License-File: LICENSE
Requires-Dist: sgtpyutils
Requires-Dist: colorlog
